[
  {
    "full_name": "Significant-Gravitas/AutoGPT",
    "stargazers_count": 177299,
    "open_issues_count": 216,
    "forks_count": 45903
  },
  {
    "full_name": "goldbergyoni/nodebestpractices",
    "stargazers_count": 103703,
    "open_issues_count": 82,
    "forks_count": 10540
  },
  {
    "full_name": "dyc3/opentogethertube",
    "stargazers_count": 446,
    "open_issues_count": 82,
    "forks_count": 56
  },
  {
    "full_name": "labs42io/clean-code-typescript",
    "stargazers_count": 9551,
    "open_issues_count": 3,
    "forks_count": 1171
  }
]