[
  {
    "full_name": "Significant-Gravitas/AutoGPT",
    "stargazers_count": 183489,
    "open_issues_count": 382,
    "forks_count": 46223
  },
  {
    "full_name": "goldbergyoni/nodebestpractices",
    "stargazers_count": 105205,
    "open_issues_count": 98,
    "forks_count": 10720
  },
  {
    "full_name": "dyc3/opentogethertube",
    "stargazers_count": 489,
    "open_issues_count": 85,
    "forks_count": 65
  },
  {
    "full_name": "labs42io/clean-code-typescript",
    "stargazers_count": 9728,
    "open_issues_count": 3,
    "forks_count": 1176
  }
]